privlib/__init__.py
privlib/anonymization/__init__.py
privlib/anonymization/src/__init__.py
privlib/anonymization/src/algorithms/__init__.py
privlib/anonymization/src/algorithms/algorithm.py
privlib/anonymization/src/algorithms/anonymization_scheme.py
privlib/anonymization/src/algorithms/differential_privacy.py
privlib/anonymization/src/algorithms/k_anonymity.py
privlib/anonymization/src/algorithms/mdav.py
privlib/anonymization/src/algorithms/microaggregation.py
privlib/anonymization/src/algorithms/t_closeness.py
privlib/anonymization/src/attribute_types/__init__.py
privlib/anonymization/src/attribute_types/attribute_type.py
privlib/anonymization/src/attribute_types/coordinate.py
privlib/anonymization/src/attribute_types/date.py
privlib/anonymization/src/attribute_types/datetime.py
privlib/anonymization/src/attribute_types/numerical_continuous.py
privlib/anonymization/src/attribute_types/numerical_discrete.py
privlib/anonymization/src/attribute_types/plain_categorical.py
privlib/anonymization/src/attribute_types/semantic_categorical_wordnet.py
privlib/anonymization/src/attribute_types/value.py
privlib/anonymization/src/entities/__init__.py
privlib/anonymization/src/entities/attribute.py
privlib/anonymization/src/entities/dataset.py
privlib/anonymization/src/entities/dataset_CSV.py
privlib/anonymization/src/entities/dataset_DataFrame.py
privlib/anonymization/src/entities/dataset_SPF.py
privlib/anonymization/src/entities/disclosure_risk_result.py
privlib/anonymization/src/entities/information_loss_result.py
privlib/anonymization/src/entities/record.py
privlib/anonymization/src/utils/__init__.py
privlib/anonymization/src/utils/constants.py
privlib/anonymization/src/utils/sensitivity_type.py
privlib/anonymization/src/utils/utils.py
privlib/antiDiscrimination/__init__.py
privlib/antiDiscrimination/src/__init__.py
privlib/antiDiscrimination/src/algorithms/__init__.py
privlib/antiDiscrimination/src/algorithms/anonymization_scheme.py
privlib-0.0.4.dist-info/LICENSE.md
privlib-0.0.4.dist-info/METADATA
privlib-0.0.4.dist-info/WHEEL
privlib-0.0.4.dist-info/top_level.txt
privlib-0.0.4.dist-info/RECORD
