Metadata-Version: 2.1
Name: privlib
Version: 0.0.4
Summary: Privacy library of the SoBigData research infrastructure
Home-page: https://github.com/pellungrobe/sbdprivacylib
Author: Roberto Pellungrini
Author-email: roberto.pellungrini@sns.it
License: BSD 3-Clause ''New'' or ''Revised'' License
Keywords: keyword1 keyword2 keyword3
Classifier: Development Status :: 4 - Beta
Classifier: Intended Audience :: Developers
Classifier: Topic :: Software Development :: Build Tools
Classifier: License :: OSI Approved :: BSD License
Classifier: Operating System :: POSIX :: Other
Classifier: Operating System :: MacOS
Classifier: Programming Language :: Python
Classifier: Programming Language :: Python :: 3
License-File: LICENSE.md
Requires-Dist: numpy (>=1.24.3)
Requires-Dist: pandas (>=1.5.3)
Requires-Dist: ipython (>=8.12.0)
Requires-Dist: tqdm (>=4.65.0)
Requires-Dist: nltk (>=3.7)
Requires-Dist: setuptools (>=66.0.0)
Requires-Dist: pyroaring (>=0.4.2)
Requires-Dist: pyfim (>=6.28)
Provides-Extra: flag
